[
  {
    "type": "custom-link",
    "label": "Giriş",
    "items": [
      {
        "type": "custom-link",
        "label": "FlowEngine Nedir?",
        "link": "/flow-engine/what-is-flow-engine"
      },
      {
        "type": "custom-link",
        "label": "FlowEngine ve Eklenti İlişkisi",
        "link": "/flow-engine/flow-engine-and-plugins"
      },
      {
        "type": "custom-link",
        "label": "Hızlı Başlangıç",
        "link": "/flow-engine/quickstart"
      },
      {
        "type": "custom-link",
        "label": "Öğrenme Yol Haritası",
        "link": "/flow-engine/learning-roadmap"
      }
    ]
  },
  {
    "type": "custom-link",
    "label": "Kılavuz",
    "items": [
      {
        "type": "custom-link",
        "label": "FlowModel Kaydı",
        "link": "/flow-engine/register-flow-model"
      },
      {
        "type": "custom-link",
        "label": "FlowModel Oluşturma",
        "link": "/flow-engine/create-flow-model"
      },
      {
        "type": "custom-link",
        "label": "FlowModel İşleme",
        "link": "/flow-engine/flow-model-renderer"
      },
      {
        "type": "custom-link",
        "label": "FlowModel Olay Akışı ve Yapılandırma",
        "link": "/flow-engine/flow-model-settings"
      },
      {
        "type": "custom-link",
        "label": "FlowModel Kalıcılığı",
        "link": "/flow-engine/flow-model-repository"
      },
      {
        "type": "custom-link",
        "label": "FlowModel Yaşam Döngüsü",
        "link": "/flow-engine/flow-model-lifecycle"
      },
      {
        "type": "custom-link",
        "label": "FlowModel Bağlam Sistemi",
        "link": "/flow-engine/flow-context"
      },
      {
        "type": "custom-link",
        "label": "Reaktif Mekanizma: Observable",
        "link": "/flow-engine/observable"
      },
      {
        "type": "custom-link",
        "label": "FlowModel vs React.Component",
        "link": "/flow-engine/flow-model-vs-react-component"
      }
    ]
  },
  {
    "type": "custom-link",
    "label": "Tanımlar",
    "items": [
      {
        "type": "custom-link",
        "label": "ModelDefinition",
        "link": "/flow-engine/definitions/model-definition"
      },
      {
        "type": "custom-link",
        "label": "FlowDefinition",
        "link": "/flow-engine/definitions/flow-definition"
      },
      {
        "type": "custom-link",
        "label": "EventDefinition",
        "link": "/flow-engine/definitions/event-definition"
      },
      {
        "type": "custom-link",
        "label": "ActionDefinition",
        "link": "/flow-engine/definitions/action-definition"
      },
      {
        "type": "custom-link",
        "label": "StepDefinition",
        "link": "/flow-engine/definitions/step-definition"
      }
    ]
  }
]
