[
  {
    "type": "custom-link",
    "label": "System Settings",
    "link": "/system-settings/"
  },
  {
    "type": "custom-link",
    "label": "Plugin Manager",
    "link": "/system-settings/plugin-manager/"
  },
  {
    "type": "custom-link",
    "label": "Language Settings",
    "link": "/system-settings/language-settings/"
  },
  {
    "type": "custom-link",
    "label": "Localization Management",
    "link": "/system-settings/localization-management/"
  },
  {
    "type": "custom-link",
    "label": "Custom Brand",
    "link": "/system-settings/custom-brand/"
  },
  {
    "type": "custom-link",
    "label": "Theme Editor",
    "link": "/system-settings/theme-editor/"
  }
]
